{"children":[{"id":2,"guid":"0hF_wMCeRvDR","title":"Bookmarks Menu","index":0,"dateAdded":1233796794912894,"lastModified":1400615090937051,"type":"text/x-moz-place-container","root":"bookmarksMenuFolder","children":[{"id":1398,"guid":"fc7y7l6TsuxY","title":"Recently Bookmarked","index":0,"dateAdded":1400615090936309,"lastModified":1400615090936673,"annos":[{"name":"Places/SmartBookmark","flags":0,"expires":4,"value":"RecentlyBookmarked"}],"type":"text/x-moz-place","uri":"place:folder=BOOKMARKS_MENU&folder=UNFILED_BOOKMARKS&folder=TOOLBAR&queryType=1&sort=12&maxResults=10&excludeQueries=1"},{"id":1399,"guid":"rVWPYZqMunfZ","title":"Recent Tags","index":1,"dateAdded":1400615090937051,"lastModified":1400615090937214,"annos":[{"name":"Places/SmartBookmark","flags":0,"expires":4,"value":"RecentTags"}],"type":"text/x-moz-place","uri":"place:type=6&sort=14&maxResults=10"},{"id":9,"guid":"RwU0zXmmK2hD","title":"","index":2,"dateAdded":1233796794927178,"lastModified":1233796794927178,"type":"text/x-moz-place-separator"},{"id":10,"guid":"dxzpHAVmKjYH","title":"Get Bookmark Add-ons","index":3,"dateAdded":1233796794931065,"lastModified":1233796794938334,"type":"text/x-moz-place","uri":"https://en-us.add-ons.mozilla.com/en-US/firefox/bookmarks/"},{"id":14,"guid":"-h8lRUPzO9YR","title":"","index":4,"dateAdded":1233796794941092,"lastModified":1233796794941092,"type":"text/x-moz-place-separator"},{"id":1295,"guid":"IMAnSc4b6RdP","title":"Reading List (From Safari)","index":5,"dateAdded":1361319623264494,"lastModified":1361319688429974,"type":"text/x-moz-place-container","children":[{"id":1296,"guid":"ApWMy7HyL1-W","title":"The Effects of Taxation on Multinational Corporations","index":0,"dateAdded":1361319623265359,"lastModified":1361319623265359,"type":"text/x-moz-place","uri":"http://www.nber.org/books/feld95-2"}]},{"id":1333,"guid":"7tpLB5NJjfnm","title":"Data Sources","index":6,"dateAdded":1361319623281152,"lastModified":1361319623285967,"type":"text/x-moz-place-container","children":[{"id":1334,"guid":"Xv1vgnKq79JY","title":"CBO","index":0,"dateAdded":1361319623282272,"lastModified":1361319623282272,"type":"text/x-moz-place","uri":"http://cbo.gov/"},{"id":1335,"guid":"-GT301QsYsm5","title":"Eurostat","index":1,"dateAdded":1361319623283366,"lastModified":1361319623283366,"type":"text/x-moz-place","uri":"http://epp.eurostat.ec.europa.eu/portal/page/portal/eurostat/home/"},{"id":1336,"guid":"JnjEkjHWu0mm","title":"FRED","index":2,"dateAdded":1361319623284021,"lastModified":1361319623284021,"type":"text/x-moz-place","uri":"http://research.stlouisfed.org/fred2/"},{"id":1337,"guid":"owA5xH5pVY4c","title":"GAO","index":3,"dateAdded":1361319623285232,"lastModified":1361319623285232,"type":"text/x-moz-place","uri":"http://gao.gov/"},{"id":1338,"guid":"X_OJ74bJ-JtE","title":"OECD","index":4,"dateAdded":1361319623285967,"lastModified":1361319623285967,"type":"text/x-moz-place","uri":"http://www.oecd.org/home/0,2987,en_2649_201185_1_1_1_1_1,00.html"}]},{"id":1339,"guid":"wYG_qduKRPaR","title":"Miscellaneous","index":7,"dateAdded":1361319623286173,"lastModified":1361319623287744,"type":"text/x-moz-place-container","children":[{"id":1340,"guid":"SCnokrmYTOPi","title":"Detexify LaTeX handwritten symbol recognition","index":0,"dateAdded":1361319623286787,"lastModified":1361319623286787,"type":"text/x-moz-place","uri":"http://detexify.kirelabs.org/classify.html"},{"id":1341,"guid":"59jNfpXzyh13","title":"Lifehacker","index":1,"dateAdded":1361319623287744,"lastModified":1361319623287744,"type":"text/x-moz-place","uri":"http://lifehacker.com/"}]},{"id":1342,"guid":"Hcz2hKGk_zWU","title":"Larger Works","index":8,"dateAdded":1361319623288028,"lastModified":1361319623289789,"type":"text/x-moz-place-container","children":[{"id":1343,"guid":"-JKehfe6jecH","title":"The Effects of Taxation on Multinational Corporations","index":0,"dateAdded":1361319623288429,"lastModified":1361319623288429,"type":"text/x-moz-place","uri":"http://www.nber.org/books/feld95-2"},{"id":1344,"guid":"iRtVODz5CsVy","title":"Stiglitz Report","index":1,"dateAdded":1361319623289155,"lastModified":1361319623289155,"type":"text/x-moz-place","uri":"http://www.stiglitz-sen-fitoussi.fr/documents/rapport_anglais.pdf"},{"id":1345,"guid":"G6mwGQDdUrNB","title":"Stiglitz Report, UN","index":2,"dateAdded":1361319623289789,"lastModified":1361319623289789,"type":"text/x-moz-place","uri":"http://www.un.org/ga/econcrisissummit/docs/FinalReport_CoE.pdf"}]},{"id":1374,"guid":"xp4AmCYDONDy","title":"Think Tanks","index":9,"dateAdded":1361319623299363,"lastModified":1361319623304098,"type":"text/x-moz-place-container","children":[{"id":1375,"guid":"YtI1FywonUVA","title":"AIER","index":0,"dateAdded":1361319623299960,"lastModified":1361319623299960,"type":"text/x-moz-place","uri":"http://www.aier.org/"},{"id":1376,"guid":"886Gu2qrheB9","title":"Brookings","index":1,"dateAdded":1361319623300653,"lastModified":1361319623300653,"type":"text/x-moz-place","uri":"http://www.brookings.edu/"},{"id":1377,"guid":"sXJl2FDocUd2","title":"Cato","index":2,"dateAdded":1361319623301140,"lastModified":1361319623301140,"type":"text/x-moz-place","uri":"http://www.cato.org/"},{"id":1378,"guid":"_Q6-heY5uz31","title":"ECRI","index":3,"dateAdded":1361319623302305,"lastModified":1361319623302305,"type":"text/x-moz-place","uri":"http://www.businesscycle.com/"},{"id":1379,"guid":"nfOyah52cgKa","title":"Rasmussen","index":4,"dateAdded":1361319623302861,"lastModified":1361319623302861,"type":"text/x-moz-place","uri":"http://www.rasmussenreports.com/","charset":"UTF-8"},{"id":1380,"guid":"1mOJEFNuRTJi","title":"Roubini","index":5,"dateAdded":1361319623303485,"lastModified":1361319623303485,"type":"text/x-moz-place","uri":"http://www.roubini.com/"},{"id":1381,"guid":"YoKy7DUXuHXw","title":"Third Way","index":6,"dateAdded":1361319623304098,"lastModified":1361319623304098,"type":"text/x-moz-place","uri":"http://thirdway.org/"}]},{"id":1382,"guid":"2OHqnd4Ymzga","title":"Working Paper/Paper Portals","index":10,"dateAdded":1361319623304282,"lastModified":1361319623308208,"type":"text/x-moz-place-container","children":[{"id":1383,"guid":"UmqtGKz3DgJ4","title":"Degruyter (UChicago)","index":0,"dateAdded":1361319623304931,"lastModified":1361319623304931,"type":"text/x-moz-place","uri":"http://www.degruyter.com.proxy.uchicago.edu/browse"},{"id":1384,"guid":"wOeOP4uHxJPn","title":"JSTOR (UChicago)","index":1,"dateAdded":1361319623305563,"lastModified":1361319623305563,"type":"text/x-moz-place","uri":"http://jstor.org/"},{"id":1385,"guid":"9Fexhy8stdkh","title":"LSE Working Papers","index":2,"dateAdded":1361319623306181,"lastModified":1361319623306181,"type":"text/x-moz-place","uri":"http://eprints.lse.ac.uk/"},{"id":1386,"guid":"RcwqQXuAmxWx","title":"SSRN BFI Working Papers","index":3,"dateAdded":1361319623306800,"lastModified":1361319623306800,"type":"text/x-moz-place","uri":"http://papers.ssrn.com/sol3/JELJOUR_Results.cfm?form_name=journalbrowse&journal_id=1335291"},{"id":1387,"guid":"73wz4ylTugIp","title":"Springerlink (UChicago)","index":4,"dateAdded":1361319623307415,"lastModified":1361319623307415,"type":"text/x-moz-place","uri":"http://www.springerlink.com.proxy.uchicago.edu/?MUD=MP"},{"id":1388,"guid":"6buV-3Z3iW2S","title":"Emmanuel Saez","index":5,"dateAdded":1361319623308208,"lastModified":1361319623308208,"type":"text/x-moz-place","uri":"http://elsa.berkeley.edu/~saez/"}]},{"id":1389,"guid":"i9AckCYTyPuJ","title":"Learning things","index":11,"dateAdded":1361319623308604,"lastModified":1361319623313941,"type":"text/x-moz-place-container","children":[{"id":1390,"guid":"eMdyDOZyNM_Z","title":"Detexify LaTeX handwritten symbol recognition","index":0,"dateAdded":1361319623308945,"lastModified":1361319623308945,"type":"text/x-moz-place","uri":"http://detexify.kirelabs.org/classify.html"},{"id":1391,"guid":"f1nFInNzlUaH","title":"MIT OCW_matlab","index":1,"dateAdded":1361319623309779,"lastModified":1361319623309779,"type":"text/x-moz-place","uri":"http://ocw.mit.edu/courses/electrical-engineering-and-computer-science/6-094-introduction-to-matlab-january-iap-2010/index.htm"},{"id":1392,"guid":"HdRr5f7TT8ON","title":"MIT OCW_mvc","index":2,"dateAdded":1361319623310470,"lastModified":1361319623310470,"type":"text/x-moz-place","uri":"http://ocw.mit.edu/courses/mathematics/18-02sc-multivariable-calculus-fall-2010/1.-vectors-and-matrices/"},{"id":1393,"guid":"gD5c7XMv67HY","title":"mathworks MATLAB intro","index":3,"dateAdded":1361319623311181,"lastModified":1361319623311181,"type":"text/x-moz-place","uri":"http://www.mathworks.com/videos/getting-started-with-matlab-68985.html"},{"id":1394,"guid":"Ww12egWClIaV","title":"mathworks MATLAB tutorial","index":4,"dateAdded":1361319623311863,"lastModified":1361319623311863,"type":"text/x-moz-place","uri":"http://www.mathworks.com/moler/chapters.html"},{"id":1395,"guid":"7ukDx0hY1iEu","title":"mathworks MATLAB demonstrations","index":5,"dateAdded":1361319623312671,"lastModified":1361319623312671,"type":"text/x-moz-place","uri":"http://blogs.mathworks.com/videos/"},{"id":1396,"guid":"jC0TeVJWXx3U","title":"mathworks MATLAB experiments tutorial","index":6,"dateAdded":1361319623313291,"lastModified":1361319623313291,"type":"text/x-moz-place","uri":"http://www.mathworks.com/moler/exm/chapters.html"},{"id":1397,"guid":"GKGv6Oat_IsO","title":"mathworks MATLAB practice","index":7,"dateAdded":1361319623313941,"lastModified":1361319623313941,"type":"text/x-moz-place","uri":"http://www.mathworks.com/matlabcentral/about/cody/"}]}]},{"id":3,"guid":"J9Eisqw5b5ZP","title":"Bookmarks Toolbar","index":1,"dateAdded":1233796794913030,"lastModified":1361319637993783,"annos":[{"name":"bookmarkProperties/description","flags":0,"expires":4,"value":"Add bookmarks to this folder to see them displayed on the Bookmarks Toolbar"}],"type":"text/x-moz-place-container","root":"toolbarFolder","children":[{"id":1244,"guid":"sknyYonf11mj","title":"Blogs","index":0,"dateAdded":1361319623209361,"lastModified":1361319623235762,"type":"text/x-moz-place-container","children":[{"id":1245,"guid":"tVpa8ueU_Las","title":"AEIdeas","index":0,"dateAdded":1361319623212966,"lastModified":1361319623212966,"type":"text/x-moz-place","uri":"http://www.aei-ideas.org/"},{"id":1246,"guid":"Cv_cnTvXeiHs","title":"Becker-Posner Blog","index":1,"dateAdded":1361319623215025,"lastModified":1361319623215025,"type":"text/x-moz-place","uri":"http://www.becker-posner-blog.com/"},{"id":1247,"guid":"IquViireWXhp","title":"Cochrane Blog","index":2,"dateAdded":1361319623216654,"lastModified":1361319623216654,"type":"text/x-moz-place","uri":"http://johnhcochrane.blogspot.com/"},{"id":1248,"guid":"33womL_sh6My","title":"Cowen Blog","index":3,"dateAdded":1361319623218141,"lastModified":1361319623218141,"type":"text/x-moz-place","uri":"http://marginalrevolution.com/"},{"id":1249,"guid":"zYbfg4SmFpwH","title":"Buttonwood","index":4,"dateAdded":1361319623219798,"lastModified":1361319623219798,"type":"text/x-moz-place","uri":"http://www.economist.com/blogs/buttonwood"},{"id":1250,"guid":"oEyC7UnTUQq-","title":"Free Exchange","index":5,"dateAdded":1361319623221566,"lastModified":1361319623221566,"type":"text/x-moz-place","uri":"http://www.economist.com/blogs/freeexchange"},{"id":1251,"guid":"hDxAVDSlcD5I","title":"Graphic Detail","index":6,"dateAdded":1361319623222581,"lastModified":1361319623222581,"type":"text/x-moz-place","uri":"http://www.economist.com/blogs/graphicdetail"},{"id":1252,"guid":"hfsRaaDwF_qj","title":"Leviathan","index":7,"dateAdded":1361319623224080,"lastModified":1361319623224080,"type":"text/x-moz-place","uri":"http://www.economist.com/blogs/leviathan"},{"id":1253,"guid":"Kag8GGoejtGW","title":"Schumpeter","index":8,"dateAdded":1361319623224921,"lastModified":1361319623224921,"type":"text/x-moz-place","uri":"http://www.economist.com/blogs/schumpeter"},{"id":1254,"guid":"Cc5gYQ6MjgA3","title":"Freakonomics","index":9,"dateAdded":1361319623226852,"lastModified":1361319623226852,"type":"text/x-moz-place","uri":"http://www.freakonomics.com/"},{"id":1255,"guid":"MxFOtQbt1Qh_","title":"Hussman Funds Blog","index":10,"dateAdded":1361319623228516,"lastModified":1361319623228516,"type":"text/x-moz-place","uri":"http://www.hussman.net/weeklyMarketComment.html"},{"id":1256,"guid":"rEa_HwRHGDoG","title":"Krugman Blog","index":11,"dateAdded":1361319623229801,"lastModified":1361319623229801,"type":"text/x-moz-place","uri":"http://krugman.blogs.nytimes.com/"},{"id":1257,"guid":"RseHD46BVKmf","title":"Mankiw Blog","index":12,"dateAdded":1361319623230500,"lastModified":1361319623230500,"type":"text/x-moz-place","uri":"http://gregmankiw.blogspot.com/"},{"id":1258,"guid":"U7uYxgRvS85A","title":"TaxVox","index":13,"dateAdded":1361319623231736,"lastModified":1361319623231736,"type":"text/x-moz-place","uri":"http://taxvox.taxpolicycenter.org/"},{"id":1259,"guid":"Q25Ld-wSBMrG","title":"Thoma Blog","index":14,"dateAdded":1361319623233120,"lastModified":1361319623233120,"type":"text/x-moz-place","uri":"http://economistsview.typepad.com/"},{"id":1260,"guid":"8Uh6iy_LmepL","title":"Warsh Blog","index":15,"dateAdded":1361319623234600,"lastModified":1361319623234600,"type":"text/x-moz-place","uri":"http://www.economicprincipals.com/"},{"id":1261,"guid":"yHlJ41fTFN1Q","title":"Wonkblog","index":16,"dateAdded":1361319623235762,"lastModified":1361319623235762,"type":"text/x-moz-place","uri":"http://www.washingtonpost.com/blogs/ezra-klein/"}]},{"id":1262,"guid":"g2iRsz8pPG5k","title":"News","index":1,"dateAdded":1361319623236100,"lastModified":1361319623261095,"type":"text/x-moz-place-container","children":[{"id":1263,"guid":"PfGz0eDpCA5d","title":"Al Jazeera","index":0,"dateAdded":1361319623238057,"lastModified":1361319623238057,"type":"text/x-moz-place","uri":"http://www.aljazeera.com/"},{"id":1264,"guid":"CEc712ARRB7X","title":"The Atlantic","index":1,"dateAdded":1361319623238570,"lastModified":1361319623238570,"type":"text/x-moz-place","uri":"http://www.theatlantic.com/"},{"id":1265,"guid":"kIrAESMmwoMU","title":"BBC","index":2,"dateAdded":1361319623239145,"lastModified":1361319623239145,"type":"text/x-moz-place","uri":"http://bbc.com/"},{"id":1266,"guid":"fAgyGjdMdZ62","title":"Bloomberg","index":3,"dateAdded":1361319623239912,"lastModified":1361319623239912,"type":"text/x-moz-place","uri":"http://bloomberg.com/"},{"id":1267,"guid":"0DGjqTxT6RtB","title":"Businessweek","index":4,"dateAdded":1361319623240276,"lastModified":1361319623240276,"type":"text/x-moz-place","uri":"http://www.businessweek.com/","charset":"UTF-8"},{"id":1268,"guid":"A4vlwBxIpIUG","title":"CS Monitor","index":5,"dateAdded":1361319623241050,"lastModified":1361319623241050,"type":"text/x-moz-place","uri":"http://csmonitor.com/"},{"id":1269,"guid":"YuPAGx-DrgG4","title":"CNNMoney","index":6,"dateAdded":1361319623241878,"lastModified":1361319623241878,"type":"text/x-moz-place","uri":"http://money.cnn.com/"},{"id":1270,"guid":"0WF9iekUIL85","title":"Econlib","index":7,"dateAdded":1361319623242917,"lastModified":1361319623242917,"type":"text/x-moz-place","uri":"http://econlib.org/"},{"id":1271,"guid":"eePbSR2d48Wr","title":"Economist","index":8,"dateAdded":1361319623243564,"lastModified":1361319623243564,"type":"text/x-moz-place","uri":"http://economist.com/"},{"id":1272,"guid":"wpozCZvaBSi8","title":"Engadget","index":9,"dateAdded":1361319623244950,"lastModified":1361319623244950,"type":"text/x-moz-place","uri":"http://engadget.com/"},{"id":1273,"guid":"sqxnyJvzlOhu","title":"Factcheck","index":10,"dateAdded":1361319623245556,"lastModified":1361319623245556,"type":"text/x-moz-place","uri":"http://factcheck.org/","charset":"UTF-8"},{"id":1274,"guid":"8A8CGCuDgDUc","title":"FT","index":11,"dateAdded":1361319623246176,"lastModified":1361319623246176,"type":"text/x-moz-place","uri":"http://ft.com/"},{"id":1275,"guid":"8Zxvkp8Zhdgj","title":"Forbes","index":12,"dateAdded":1361319623247171,"lastModified":1361319623247171,"type":"text/x-moz-place","uri":"http://forbes.com/"},{"id":1276,"guid":"KQZ6oFSyrAT-","title":"Fortune","index":13,"dateAdded":1361319623247561,"lastModified":1361319623247561,"type":"text/x-moz-place","uri":"http://money.cnn.com/magazines/fortune/","charset":"ISO-8859-1"},{"id":1277,"guid":"ARZ_EM1z7o-Q","title":"HBR","index":14,"dateAdded":1361319623248086,"lastModified":1361319623248086,"type":"text/x-moz-place","uri":"http://hbr.org/"},{"id":1278,"guid":"XAUukJ_aMqIF","title":"HuffPo","index":15,"dateAdded":1361319623249548,"lastModified":1361319623249548,"type":"text/x-moz-place","uri":"http://huffingtonpost.com/"},{"id":1279,"guid":"lHXpVsyzocI_","title":"Money","index":16,"dateAdded":1361319623250188,"lastModified":1361319623250188,"type":"text/x-moz-place","uri":"http://money.cnn.com/magazines/moneymag/"},{"id":1280,"guid":"48m5l9ihIuMZ","title":"NYTimes","index":17,"dateAdded":1361319623250808,"lastModified":1361319623250808,"type":"text/x-moz-place","uri":"http://nytimes.com/"},{"id":1281,"guid":"4GCu60JcQyXW","title":"Politico","index":18,"dateAdded":1361319623251441,"lastModified":1361319623251441,"type":"text/x-moz-place","uri":"http://politico.com/"},{"id":1282,"guid":"vNepaKDsM4Z-","title":"Politifact","index":19,"dateAdded":1361319623252073,"lastModified":1361319623252073,"type":"text/x-moz-place","uri":"http://politifact.com/"},{"id":1283,"guid":"lJWVn5h0Nrsl","title":"Reason","index":20,"dateAdded":1361319623252415,"lastModified":1361319623252415,"type":"text/x-moz-place","uri":"http://reason.com/","charset":"UTF-8"},{"id":1284,"guid":"ldbNuKDNlXkL","title":"Reuters","index":21,"dateAdded":1361319623253638,"lastModified":1361319623253638,"type":"text/x-moz-place","uri":"http://reuters.com/"},{"id":1285,"guid":"X2uGngF1Au9Y","title":"SciAm","index":22,"dateAdded":1361319623254565,"lastModified":1361319623254565,"type":"text/x-moz-place","uri":"http://scientificamerican.com/"},{"id":1286,"guid":"aP6l1C661wvu","title":"Science Daily","index":23,"dateAdded":1361319623255498,"lastModified":1361319623255498,"type":"text/x-moz-place","uri":"http://sciencedaily.com/"},{"id":1287,"guid":"E0FUL8fyacqZ","title":"Time","index":24,"dateAdded":1361319623256691,"lastModified":1361319623256691,"type":"text/x-moz-place","uri":"http://time.com/"},{"id":1288,"guid":"L10kzKDn7mWj","title":"Trading Economics","index":25,"dateAdded":1361319623257625,"lastModified":1361319623257625,"type":"text/x-moz-place","uri":"http://www.tradingeconomics.com/"},{"id":1289,"guid":"LutJtldUi_f-","title":"The Verge","index":26,"dateAdded":1361319623258825,"lastModified":1361319623258825,"type":"text/x-moz-place","uri":"http://www.theverge.com/"},{"id":1290,"guid":"IjPKj-W9KqYJ","title":"Wired","index":27,"dateAdded":1361319623260100,"lastModified":1361319623260100,"type":"text/x-moz-place","uri":"http://wired.com/"},{"id":1291,"guid":"zjDZW2MOdwSy","title":"WSJ","index":28,"dateAdded":1361319623260456,"lastModified":1361319623260456,"type":"text/x-moz-place","uri":"http://online.wsj.com/home-page","charset":"UTF-8"},{"id":1292,"guid":"1RCBfdE3kDhF","title":"Yahoo! News","index":29,"dateAdded":1361319623261095,"lastModified":1361319623261095,"type":"text/x-moz-place","uri":"http://news.yahoo.com/"}]},{"id":1293,"guid":"2QuD3VXGjmAz","title":"My UoC","index":2,"dateAdded":1361319623262164,"lastModified":1361333731559856,"type":"text/x-moz-place","uri":"http://my.uchicago.edu/"},{"id":1294,"guid":"IfwbzUIsarXb","title":"Chalk UoC","index":3,"dateAdded":1361319623263865,"lastModified":1361319623263865,"type":"text/x-moz-place","uri":"https://chalk.uchicago.edu/webapps/portal/frameset.jsp"}]},{"id":5,"guid":"iOH9eMYnowDi","title":"Unsorted Bookmarks","index":3,"dateAdded":1233796794913293,"lastModified":1361319714057334,"annos":[{"name":"bookmarkPropertiesDialog/folderLastUsed","flags":0,"expires":4,"value":1238218770958}],"type":"text/x-moz-place-container","root":"unfiledBookmarksFolder","children":[{"id":1074,"guid":"2RVe4aec_QF8","title":"Games","index":0,"dateAdded":1304921425008910,"lastModified":1304921887307528,"type":"text/x-moz-place-container","children":[{"id":781,"guid":"3ZF8-i9_-Zpr","title":"Tower of Greed - Jay is Games","index":0,"dateAdded":1248237389265849,"lastModified":1248237389328830,"annos":[{"name":"bookmarkProperties/description","flags":0,"expires":4,"value":"We recommend and review the best casual games available on the Web today. Including walkthroughs, discussions and game links for browser games and downloadable computer games. Focused on hidden object, escape-the-room, puzzle, point-and-click, arcade and adventure games."}],"type":"text/x-moz-place","uri":"http://jayisgames.com/games/tower-of-greed/","charset":"UTF-8"},{"id":1096,"guid":"L-oWevIdTdpD","title":"Funny","index":1,"dateAdded":1304921887307528,"lastModified":1304921890812377,"type":"text/x-moz-place-container"}]},{"id":1315,"guid":"GUOiHjnvNP5s","title":"Iphone moviez","index":1,"dateAdded":1361319623274905,"lastModified":1361319623274905,"type":"text/x-moz-place","uri":"http://iphonemoviez.net/blog/unmanaged-dedicated-server-colohosting-webhost/"},{"id":1316,"guid":"WCQ1fz2aLNJh","title":"faad","index":2,"dateAdded":1361319623275516,"lastModified":1361319623275516,"type":"text/x-moz-place","uri":"http://freeappaday.com/"}]}]}